README.rst
setup.cfg
setup.py
buckshot/__init__.py
buckshot/constants.py
buckshot/contexts.py
buckshot/datautils.py
buckshot/decorators.py
buckshot/distributors.py
buckshot/errors.py
buckshot/funcutils.py
buckshot/listener.py
buckshot/lockutils.py
buckshot/logutils.py
buckshot/procutils.py
buckshot/signals.py
buckshot/tasks.py
buckshot/threads.py
buckshot/version.py
buckshot.egg-info/PKG-INFO
buckshot.egg-info/SOURCES.txt
buckshot.egg-info/dependency_links.txt
buckshot.egg-info/pbr.json
buckshot.egg-info/requires.txt
buckshot.egg-info/top_level.txt