Metadata-Version: 1.0
Name: buckshot
Version: 0.0.10
Summary: Scatters tasks across processes.
Home-page: https://github.com/bworrell
Author: Bryan Worrell
Author-email: bworrell@notmyemail.com
License: UNKNOWN
Keywords: buckshot distrubted concurrency mp multiprocesses multiprocessing generally terrible
Platform: UNKNOWN
